__init__.py
blasto.py
datastore/Memo.py
datastore/Record.py
datastore/RecordStore.py
datastore/__init__.py
monitoring/ExportReport.py
monitoring/Logger.py
monitoring/Profiler.py
monitoring/Stats.py
monitoring/__init__.py
projects/__init__.py
resources/__init__.py
resources/mapfiles/__init__.py
resources/validation/__init__.py
setup/InputList.py
setup/Mapper.py
setup/Settings.py
setup/Validator.py
setup/__init__.py
util/CoordinateWorkaround.py
util/ExportHandler.py
util/Harvester.py
util/Output.py
util/ProcessingFunctions.py
util/Processor.py
util/RelationshipOutput.py
util/Writer.py
util/__init__.py
blastochor-0.1.3.dist-info/METADATA
blastochor-0.1.3.dist-info/WHEEL
blastochor-0.1.3.dist-info/top_level.txt
blastochor-0.1.3.dist-info/RECORD
