Metadata-Version: 2.1
Name: blastochor
Version: 0.1.3
Summary: Harvest, transform, and export data from Te Papa's collections API.
Author-email: Lucy Schrader <lucy@schrader.nz>
License: MIT License
Project-URL: Homepage, https://github.com/lucyschrader/Blastochor
Keywords: python,museum,api
Classifier: Development Status :: 4 - Beta
Classifier: License :: OSI Approved :: MIT License
Classifier: Intended Audience :: Education
Classifier: Programming Language :: Python :: 3
Classifier: Natural Language :: English
Requires-Python: >=3.7
